{
  "createdAt": "2023-01-10T13:16:43.979Z",
  "updatedAt": "2023-01-10T13:16:43.944Z",
  "id": "2",
  "name": "Header Auth account",
  "data": "U2FsdGVkX1+vpEslrA1Z9mFclK+XxcNwQ4d95AEH/tFUlOtRs3ZH6QvHgNfOo6cspYJxkOC3u+Nxd7VfMyMUIg==",
  "type": "httpHeaderAuth",
  "nodesAccess": [
    {
      "nodeType": "n8n-nodes-base.graphql",
      "date": "2023-01-10T13:16:43.921Z"
    },
    {
      "nodeType": "n8n-nodes-base.wait",
      "date": "2023-01-10T13:16:43.921Z"
    },
    {
      "nodeType": "n8n-nodes-base.webhook",
      "date": "2023-01-10T13:16:43.921Z"
    }
  ]
}