{
  "createdAt": "2023-01-10T13:23:33.576Z",
  "updatedAt": "2023-02-20T11:33:33.804Z",
  "id": "3",
  "name": "Header Auth account 2",
  "data": "U2FsdGVkX181zaMAX7xJeIsNJB7fpGxFdyowaYdqrqoWJJUTjC1jGYCYFNUfar0dHLkqgNTRPjLjhgLC6Mr8R/JSohCL+YEtjaiiGjJH9l+tEMobmgWuqeIN76Qxaz72zuuh6X2q3VJAGB72Mrht6A==",
  "type": "httpHeaderAuth",
  "nodesAccess": [
    {
      "nodeType": "n8n-nodes-base.graphql",
      "date": "2023-01-10T13:23:33.493Z"
    },
    {
      "nodeType": "n8n-nodes-base.wait",
      "date": "2023-01-10T13:23:33.493Z"
    },
    {
      "nodeType": "n8n-nodes-base.webhook",
      "date": "2023-01-10T13:23:33.493Z"
    }
  ]
}